setup.py
ymci_ext_source_git/__init__.py
ymci_ext_source_git/git.py
ymci_ext_source_git.egg-info/PKG-INFO
ymci_ext_source_git.egg-info/SOURCES.txt
ymci_ext_source_git.egg-info/dependency_links.txt
ymci_ext_source_git.egg-info/entry_points.txt
ymci_ext_source_git.egg-info/top_level.txt