Metadata-Version: 1.1
Name: ymci-ext-source-git
Version: 1.1
Summary: Git source plugin for ymci
Home-page: UNKNOWN
Author: Florian Mounier, Kozea
Author-email: florian.mounier@kozea.fr
License: UNKNOWN
Platform: Any
Provides: ymci_ext_source_git
